setup.py
anthill_modules.core.egg-info/PKG-INFO
anthill_modules.core.egg-info/SOURCES.txt
anthill_modules.core.egg-info/dependency_links.txt
anthill_modules.core.egg-info/top_level.txt
get_system_info/__init__.py
get_system_info/get_system_info.py
utils/__init__.py
utils/run_command_async.py