Metadata-Version: 2.1
Name: anthill-modules.core
Version: 0.1.0
Summary: Anthill Core module
Author: Nix
